pyraster/__init__.py
pyraster/dataset.py
pyraster-0.1.1.dist-info/LICENSE
pyraster-0.1.1.dist-info/METADATA
pyraster-0.1.1.dist-info/WHEEL
pyraster-0.1.1.dist-info/top_level.txt
pyraster-0.1.1.dist-info/RECORD
