Metadata-Version: 2.1
Name: pyraster
Version: 0.1.1
Summary: Python tools for processing raster and vector data for deep learning applications. GDAL needs to be installed already.
Home-page: https://github.com/bashirkazimi/pyraster
Author: Bashir Kazimi
Author-email: kazimibashir907@gmail.com
License: Apache License 2.0
Platform: UNKNOWN
